MANIFEST.in
README.rst
setup.py
sendgrid_parse/__init__.py
sendgrid_parse/errors.py
sendgrid_parse/parse.py
sendgrid_parse.egg-info/PKG-INFO
sendgrid_parse.egg-info/SOURCES.txt
sendgrid_parse.egg-info/dependency_links.txt
sendgrid_parse.egg-info/not-zip-safe
sendgrid_parse.egg-info/top_level.txt