Metadata-Version: 1.1
Name: sendgrid-parse
Version: 0.2
Summary: Access SendGrid's Inbound Parse emails into a dictionary
Home-page: https://github.com/coolharsh55/sendgrid_parse
Author: coolharsh55
Author-email: me@harshp.com
License: MIT
Keywords: sendgrid inbound parse email flask django
Platform: UNKNOWN
Classifier: Development Status :: 4 - Beta
Classifier: License :: OSI Approved :: MIT License
Classifier: Programming Language :: Python
Classifier: Topic :: Communications :: Email
